asv_runner-0.2.0.dist-info/METADATA
asv_runner-0.2.0.dist-info/WHEEL
asv_runner-0.2.0.dist-info/licenses/LICENSE.md
asv_runner/__init__.py
asv_runner/_aux.py
asv_runner/benchmarks/__init__.py
asv_runner/benchmarks/_base.py
asv_runner/benchmarks/_exceptions.py
asv_runner/benchmarks/_maxrss.py
asv_runner/benchmarks/mark.py
asv_runner/benchmarks/mem.py
asv_runner/benchmarks/peakmem.py
asv_runner/benchmarks/time.py
asv_runner/benchmarks/timeraw.py
asv_runner/benchmarks/track.py
asv_runner/check.py
asv_runner/console.py
asv_runner/discovery.py
asv_runner/run.py
asv_runner/server.py
asv_runner/setup_cache.py
asv_runner/statistics.py
asv_runner/timing.py
asv_runner/util.py
asv_runner-0.2.0.dist-info/RECORD
