Metadata-Version: 2.1
Name: asv_runner
Version: 0.2.0
Summary: Core Python benchmark code for ASV
Home-page: https://asv.readthedocs.io/projects/asv-runner/en/latest/
Author-Email: Rohit Goswami <rog32@hi.is>, Michael Droettboom <mdroe@stsci.edu>
Maintainer-Email: Rohit Goswami <rog32@hi.is>
License: BSD-3-Clause
Classifier: Development Status :: 4 - Beta
Classifier: Programming Language :: Python
Classifier: License :: OSI Approved :: BSD License
Classifier: Programming Language :: Python :: 3
Classifier: Programming Language :: Python :: 3 :: Only
Classifier: Programming Language :: Python :: 3.7
Classifier: Programming Language :: Python :: 3.8
Classifier: Programming Language :: Python :: 3.9
Classifier: Programming Language :: Python :: 3.10
Classifier: Programming Language :: Python :: 3.11
Classifier: Programming Language :: Python :: 3.12
Classifier: Topic :: System :: Benchmark
Project-URL: Homepage, https://asv.readthedocs.io/projects/asv-runner/en/latest/
Project-URL: Repository, https://github.com/airspeed-velocity/asv_runner
Project-URL: Documentation, https://asv.readthedocs.io/projects/asv-runner/en/latest/
Requires-Python: >=3.7
Provides-Extra: docs
Requires-Dist: furo; extra == "docs"
Requires-Dist: sphinx; extra == "docs"
Requires-Dist: sphinx-contributors; extra == "docs"
Requires-Dist: sphinx-copybutton; extra == "docs"
Requires-Dist: sphinx-design; extra == "docs"
Requires-Dist: sphinx-autobuild; extra == "docs"
Requires-Dist: sphinxcontrib-spelling; extra == "docs"
Requires-Dist: myst-parser>=2; extra == "docs"
Requires-Dist: sphinx-autodoc2>=0.4.2; extra == "docs"
